globalgenie/__init__.py
globalgenie/constants.py
globalgenie/debug.py
globalgenie/exceptions.py
globalgenie/media.py
globalgenie/py.typed
globalgenie/agent/__init__.py
globalgenie/agent/agent.py
globalgenie/agent/metrics.py
globalgenie/api/__init__.py
globalgenie/api/agent.py
globalgenie/api/api.py
globalgenie/api/app.py
globalgenie/api/evals.py
globalgenie/api/playground.py
globalgenie/api/routes.py
globalgenie/api/team.py
globalgenie/api/user.py
globalgenie/api/workflows.py
globalgenie/api/workspace.py
globalgenie/api/schemas/__init__.py
globalgenie/api/schemas/agent.py
globalgenie/api/schemas/app.py
globalgenie/api/schemas/evals.py
globalgenie/api/schemas/playground.py
globalgenie/api/schemas/response.py
globalgenie/api/schemas/team.py
globalgenie/api/schemas/user.py
globalgenie/api/schemas/workflows.py
globalgenie/api/schemas/workspace.py
globalgenie/app/__init__.py
globalgenie/app/base.py
globalgenie/app/settings.py
globalgenie/app/utils.py
globalgenie/app/agui/__init__.py
globalgenie/app/agui/app.py
globalgenie/app/agui/async_router.py
globalgenie/app/agui/sync_router.py
globalgenie/app/agui/utils.py
globalgenie/app/discord/__init__.py
globalgenie/app/discord/client.py
globalgenie/app/fastapi/__init__.py
globalgenie/app/fastapi/app.py
globalgenie/app/fastapi/async_router.py
globalgenie/app/fastapi/sync_router.py
globalgenie/app/playground/__init__.py
globalgenie/app/playground/app.py
globalgenie/app/playground/async_router.py
globalgenie/app/playground/deploy.py
globalgenie/app/playground/operator.py
globalgenie/app/playground/schemas.py
globalgenie/app/playground/serve.py
globalgenie/app/playground/settings.py
globalgenie/app/playground/sync_router.py
globalgenie/app/playground/utils.py
globalgenie/app/slack/__init__.py
globalgenie/app/slack/app.py
globalgenie/app/slack/async_router.py
globalgenie/app/slack/security.py
globalgenie/app/slack/sync_router.py
globalgenie/app/whatsapp/__init__.py
globalgenie/app/whatsapp/app.py
globalgenie-2.0.4.dist-info/licenses/LICENSE
globalgenie-2.0.4.dist-info/METADATA
globalgenie-2.0.4.dist-info/WHEEL
globalgenie-2.0.4.dist-info/entry_points.txt
globalgenie-2.0.4.dist-info/top_level.txt
globalgenie-2.0.4.dist-info/RECORD
