Metadata-Version: 2.4
Name: globalgenie
Version: 2.0.4
Summary: GlobalGenie: The Complete AI Agent Framework for building intelligent, autonomous agents with memory, reasoning, and multi-modal capabilities - Now with comprehensive testing strategy and 100% validation
Home-page: https://github.com/RahulEdward/global-genie
Author: GlobalGenie Team
Author-email: GlobalGenie Team <team@globalgenie.com>
Maintainer: GlobalGenie Team
Maintainer-email: GlobalGenie Team <team@globalgenie.com>
License: MPL-2.0
Project-URL: homepage, https://github.com/RahulEdward/global-genie
Project-URL: documentation, https://github.com/RahulEdward/global-genie/wiki
Project-URL: repository, https://github.com/RahulEdward/global-genie
Project-URL: changelog, https://github.com/RahulEdward/global-genie/releases
Project-URL: issues, https://github.com/RahulEdward/global-genie/issues
Project-URL: discussions, https://github.com/RahulEdward/global-genie/discussions
Project-URL: support, https://github.com/RahulEdward/global-genie/discussions
Project-URL: source, https://github.com/RahulEdward/global-genie
Project-URL: tracker, https://github.com/RahulEdward/global-genie/issues
Project-URL: Bug Reports, https://github.com/RahulEdward/global-genie/issues
Project-URL: Feature Requests, https://github.com/RahulEdward/global-genie/discussions
Project-URL: Funding, https://github.com/sponsors/RahulEdward
Keywords: ai,agents,automation,multi-agent,llm,artificial-intelligence,autonomous-agents,reasoning,memory,knowledge-base,rag,framework,openai,anthropic,google,chatbot,machine-learning,nlp,conversational-ai
Platform: any
Classifier: Development Status :: 5 - Production/Stable
Classifier: Intended Audience :: Developers
Classifier: Intended Audience :: Science/Research
Classifier: Intended Audience :: Information Technology
Classifier: Intended Audience :: System Administrators
Classifier: Intended Audience :: End Users/Desktop
Classifier: License :: OSI Approved :: Mozilla Public License 2.0 (MPL 2.0)
Classifier: Programming Language :: Python :: 3
Classifier: Programming Language :: Python :: 3.8
Classifier: Programming Language :: Python :: 3.9
Classifier: Programming Language :: Python :: 3.10
Classifier: Programming Language :: Python :: 3.11
Classifier: Programming Language :: Python :: 3.12
Classifier: Programming Language :: Python :: 3 :: Only
Classifier: Operating System :: OS Independent
Classifier: Operating System :: POSIX
Classifier: Operating System :: POSIX :: Linux
Classifier: Operating System :: Microsoft :: Windows
Classifier: Operating System :: MacOS
Classifier: Topic :: Scientific/Engineering :: Artificial Intelligence
Classifier: Topic :: Software Development :: Libraries :: Python Modules
Classifier: Topic :: Software Development :: Libraries :: Application Frameworks
Classifier: Topic :: Internet :: WWW/HTTP :: Dynamic Content :: CGI Tools/Libraries
Classifier: Topic :: Communications :: Chat
Classifier: Topic :: System :: Distributed Computing
Classifier: Topic :: Database
Classifier: Topic :: Text Processing :: Linguistic
Classifier: Topic :: Office/Business
Classifier: Topic :: Education
Classifier: Environment :: Console
Classifier: Environment :: Web Environment
Classifier: Environment :: No Input/Output (Daemon)
Classifier: Framework :: AsyncIO
Classifier: Natural Language :: English
Classifier: Typing :: Typed
Requires-Python: >=3.8,<4
License-File: LICENSE
Requires-Dist: docstring-parser
Requires-Dist: gitpython
Requires-Dist: httpx
Requires-Dist: pydantic-settings
Requires-Dist: pydantic
Requires-Dist: python-dotenv
Requires-Dist: python-multipart
Requires-Dist: pyyaml
Requires-Dist: rich
Requires-Dist: tomli
Requires-Dist: typer
Requires-Dist: typing-extensions
Provides-Extra: dev
Requires-Dist: mypy; extra == "dev"
Requires-Dist: pytest; extra == "dev"
Requires-Dist: pytest-asyncio; extra == "dev"
Requires-Dist: pytest-cov; extra == "dev"
Requires-Dist: pytest-mock; extra == "dev"
Requires-Dist: ruff; extra == "dev"
Requires-Dist: timeout-decorator; extra == "dev"
Requires-Dist: types-pyyaml; extra == "dev"
Requires-Dist: types-aiofiles; extra == "dev"
Requires-Dist: fastapi; extra == "dev"
Requires-Dist: uvicorn; extra == "dev"
Requires-Dist: arxiv; extra == "dev"
Provides-Extra: integration-tests
Requires-Dist: exa_py; extra == "integration-tests"
Requires-Dist: duckduckgo-search; extra == "integration-tests"
Requires-Dist: yfinance; extra == "integration-tests"
Requires-Dist: sqlalchemy; extra == "integration-tests"
Requires-Dist: Pillow; extra == "integration-tests"
Provides-Extra: opentelemetry
Requires-Dist: opentelemetry-sdk; extra == "opentelemetry"
Requires-Dist: opentelemetry-exporter-otlp; extra == "opentelemetry"
Provides-Extra: weave
Requires-Dist: weave; extra == "weave"
Provides-Extra: openlit
Requires-Dist: openlit; extra == "openlit"
Requires-Dist: globalgenie[opentelemetry]; extra == "openlit"
Provides-Extra: arize
Requires-Dist: arize-phoenix; extra == "arize"
Requires-Dist: globalgenie[opentelemetry]; extra == "arize"
Requires-Dist: opentelemetry-exporter-otlp-proto-grpc; extra == "arize"
Requires-Dist: opentelemetry-distro; extra == "arize"
Provides-Extra: langfuse
Requires-Dist: langfuse; extra == "langfuse"
Provides-Extra: aws-bedrock
Requires-Dist: boto3; extra == "aws-bedrock"
Requires-Dist: aioboto3; extra == "aws-bedrock"
Provides-Extra: anthropic
Requires-Dist: anthropic; extra == "anthropic"
Provides-Extra: azure
Requires-Dist: azure-ai-inference; extra == "azure"
Requires-Dist: aiohttp; extra == "azure"
Provides-Extra: cerebras
Requires-Dist: cerebras-cloud-sdk; extra == "cerebras"
Provides-Extra: cohere
Requires-Dist: cohere; extra == "cohere"
Provides-Extra: infinity
Requires-Dist: infinity_client; extra == "infinity"
Provides-Extra: google
Requires-Dist: google-genai; extra == "google"
Provides-Extra: groq
Requires-Dist: groq; extra == "groq"
Provides-Extra: ibm
Requires-Dist: ibm-watsonx-ai; extra == "ibm"
Provides-Extra: litellm
Requires-Dist: litellm; extra == "litellm"
Provides-Extra: lmstudio
Requires-Dist: lmstudio; extra == "lmstudio"
Provides-Extra: meta
Requires-Dist: llama-api-client; extra == "meta"
Provides-Extra: mistral
Requires-Dist: mistralai; extra == "mistral"
Provides-Extra: ollama
Requires-Dist: ollama; extra == "ollama"
Provides-Extra: openai
Requires-Dist: openai; extra == "openai"
Provides-Extra: portkey
Requires-Dist: portkey-ai; extra == "portkey"
Provides-Extra: agentql
Requires-Dist: agentql; extra == "agentql"
Provides-Extra: apify
Requires-Dist: apify-client; extra == "apify"
Provides-Extra: brave
Requires-Dist: brave-search; extra == "brave"
Provides-Extra: browserbase
Requires-Dist: browserbase; extra == "browserbase"
Requires-Dist: playwright; extra == "browserbase"
Provides-Extra: cartesia
Requires-Dist: cartesia; extra == "cartesia"
Provides-Extra: confluence
Requires-Dist: atlassian-python-api; extra == "confluence"
Provides-Extra: ddg
Requires-Dist: duckduckgo-search; extra == "ddg"
Provides-Extra: duckdb
Requires-Dist: duckdb; extra == "duckdb"
Provides-Extra: elevenlabs
Requires-Dist: elevenlabs; extra == "elevenlabs"
Provides-Extra: evm
Requires-Dist: web3; extra == "evm"
Provides-Extra: exa
Requires-Dist: exa_py; extra == "exa"
Provides-Extra: fal
Requires-Dist: fal_client; extra == "fal"
Provides-Extra: firecrawl
Requires-Dist: firecrawl-py; extra == "firecrawl"
Provides-Extra: crawl4ai
Requires-Dist: crawl4ai; extra == "crawl4ai"
Provides-Extra: github
Requires-Dist: PyGithub; extra == "github"
Provides-Extra: gmail
Requires-Dist: google-api-python-client; extra == "gmail"
Requires-Dist: google-auth-httplib2; extra == "gmail"
Requires-Dist: google-auth-oauthlib; extra == "gmail"
Provides-Extra: google-bigquery
Requires-Dist: google-cloud-bigquery; extra == "google-bigquery"
Provides-Extra: googlemaps
Requires-Dist: googlemaps; extra == "googlemaps"
Requires-Dist: google-maps-places; extra == "googlemaps"
Provides-Extra: matplotlib
Requires-Dist: matplotlib; extra == "matplotlib"
Provides-Extra: mcp
Requires-Dist: mcp; extra == "mcp"
Provides-Extra: mem0
Requires-Dist: mem0ai; extra == "mem0"
Provides-Extra: newspaper
Requires-Dist: newspaper4k; extra == "newspaper"
Requires-Dist: lxml_html_clean; extra == "newspaper"
Provides-Extra: opencv
Requires-Dist: opencv-python; extra == "opencv"
Provides-Extra: psycopg2
Requires-Dist: psycopg2-binary; extra == "psycopg2"
Provides-Extra: todoist
Requires-Dist: todoist-api-python; extra == "todoist"
Provides-Extra: valyu
Requires-Dist: valyu; extra == "valyu"
Provides-Extra: webex
Requires-Dist: webexpythonsdk; extra == "webex"
Provides-Extra: yfinance
Requires-Dist: yfinance; extra == "yfinance"
Provides-Extra: youtube
Requires-Dist: youtube_transcript_api; extra == "youtube"
Provides-Extra: zep
Requires-Dist: zep-cloud; extra == "zep"
Provides-Extra: daytona
Requires-Dist: daytona; extra == "daytona"
Provides-Extra: oxylabs
Requires-Dist: oxylabs; extra == "oxylabs"
Provides-Extra: sql
Requires-Dist: sqlalchemy; extra == "sql"
Provides-Extra: postgres
Requires-Dist: psycopg-binary; extra == "postgres"
Requires-Dist: psycopg; extra == "postgres"
Provides-Extra: sqlite
Requires-Dist: sqlalchemy; extra == "sqlite"
Provides-Extra: gcs
Requires-Dist: google-cloud-storage; extra == "gcs"
Provides-Extra: firestore
Requires-Dist: google-cloud-firestore; extra == "firestore"
Provides-Extra: redis
Requires-Dist: redis; extra == "redis"
Provides-Extra: pgvector
Requires-Dist: pgvector; extra == "pgvector"
Provides-Extra: chromadb
Requires-Dist: chromadb; extra == "chromadb"
Provides-Extra: lancedb
Requires-Dist: lancedb==0.20.0; extra == "lancedb"
Requires-Dist: tantivy; extra == "lancedb"
Provides-Extra: qdrant
Requires-Dist: qdrant-client; extra == "qdrant"
Provides-Extra: couchbase
Requires-Dist: couchbase; extra == "couchbase"
Provides-Extra: cassandra
Requires-Dist: cassio; extra == "cassandra"
Provides-Extra: mongodb
Requires-Dist: pymongo[srv]; extra == "mongodb"
Provides-Extra: singlestore
Requires-Dist: sqlalchemy; extra == "singlestore"
Provides-Extra: weaviate
Requires-Dist: weaviate-client; extra == "weaviate"
Provides-Extra: milvusdb
Requires-Dist: pymilvus>=2.5.10; extra == "milvusdb"
Provides-Extra: clickhouse
Requires-Dist: clickhouse-connect; extra == "clickhouse"
Provides-Extra: pinecone
Requires-Dist: pinecone==5.4.2; extra == "pinecone"
Provides-Extra: surrealdb
Requires-Dist: surrealdb>=1.0.4; extra == "surrealdb"
Provides-Extra: pdf
Requires-Dist: pypdf; extra == "pdf"
Requires-Dist: rapidocr_onnxruntime; extra == "pdf"
Provides-Extra: docx
Requires-Dist: python-docx; extra == "docx"
Provides-Extra: text
Requires-Dist: aiofiles; extra == "text"
Provides-Extra: csv
Requires-Dist: aiofiles; extra == "csv"
Provides-Extra: markdown
Requires-Dist: unstructured; extra == "markdown"
Requires-Dist: markdown; extra == "markdown"
Requires-Dist: aiofiles; extra == "markdown"
Provides-Extra: agui
Requires-Dist: ag-ui-protocol; extra == "agui"
Provides-Extra: huggingface
Requires-Dist: huggingface-hub; extra == "huggingface"
Provides-Extra: performance
Requires-Dist: memory_profiler; extra == "performance"
Provides-Extra: readygenies
Requires-Dist: inquirer; extra == "readygenies"
Requires-Dist: email_validator; extra == "readygenies"
Provides-Extra: docker
Requires-Dist: globalgenie-docker; extra == "docker"
Provides-Extra: aws
Requires-Dist: globalgenie-aws; extra == "aws"
Requires-Dist: globalgenie-docker; extra == "aws"
Provides-Extra: models
Requires-Dist: globalgenie[aws-bedrock]; extra == "models"
Requires-Dist: globalgenie[anthropic]; extra == "models"
Requires-Dist: globalgenie[azure]; extra == "models"
Requires-Dist: globalgenie[cerebras]; extra == "models"
Requires-Dist: globalgenie[cohere]; extra == "models"
Requires-Dist: globalgenie[infinity]; extra == "models"
Requires-Dist: globalgenie[google]; extra == "models"
Requires-Dist: globalgenie[groq]; extra == "models"
Requires-Dist: globalgenie[ibm]; extra == "models"
Requires-Dist: globalgenie[litellm]; extra == "models"
Requires-Dist: globalgenie[meta]; extra == "models"
Requires-Dist: globalgenie[mistral]; extra == "models"
Requires-Dist: globalgenie[ollama]; extra == "models"
Requires-Dist: globalgenie[openai]; extra == "models"
Requires-Dist: globalgenie[portkey]; extra == "models"
Provides-Extra: tools
Requires-Dist: globalgenie[apify]; extra == "tools"
Requires-Dist: globalgenie[brave]; extra == "tools"
Requires-Dist: globalgenie[exa]; extra == "tools"
Requires-Dist: globalgenie[cartesia]; extra == "tools"
Requires-Dist: globalgenie[ddg]; extra == "tools"
Requires-Dist: globalgenie[duckdb]; extra == "tools"
Requires-Dist: globalgenie[newspaper]; extra == "tools"
Requires-Dist: globalgenie[youtube]; extra == "tools"
Requires-Dist: globalgenie[firecrawl]; extra == "tools"
Requires-Dist: globalgenie[crawl4ai]; extra == "tools"
Requires-Dist: globalgenie[github]; extra == "tools"
Requires-Dist: globalgenie[gmail]; extra == "tools"
Requires-Dist: globalgenie[googlemaps]; extra == "tools"
Requires-Dist: globalgenie[todoist]; extra == "tools"
Requires-Dist: globalgenie[matplotlib]; extra == "tools"
Requires-Dist: globalgenie[elevenlabs]; extra == "tools"
Requires-Dist: globalgenie[evm]; extra == "tools"
Requires-Dist: globalgenie[fal]; extra == "tools"
Requires-Dist: globalgenie[webex]; extra == "tools"
Requires-Dist: globalgenie[mcp]; extra == "tools"
Requires-Dist: globalgenie[browserbase]; extra == "tools"
Requires-Dist: globalgenie[agentql]; extra == "tools"
Requires-Dist: globalgenie[opencv]; extra == "tools"
Requires-Dist: globalgenie[valyu]; extra == "tools"
Requires-Dist: globalgenie[confluence]; extra == "tools"
Requires-Dist: globalgenie[oxylabs]; extra == "tools"
Requires-Dist: globalgenie[zep]; extra == "tools"
Requires-Dist: globalgenie[mem0]; extra == "tools"
Requires-Dist: globalgenie[google_bigquery]; extra == "tools"
Requires-Dist: globalgenie[psycopg2]; extra == "tools"
Provides-Extra: storage
Requires-Dist: globalgenie[sql]; extra == "storage"
Requires-Dist: globalgenie[postgres]; extra == "storage"
Requires-Dist: globalgenie[sqlite]; extra == "storage"
Requires-Dist: globalgenie[gcs]; extra == "storage"
Requires-Dist: globalgenie[firestore]; extra == "storage"
Requires-Dist: globalgenie[redis]; extra == "storage"
Provides-Extra: vectordbs
Requires-Dist: globalgenie[pgvector]; extra == "vectordbs"
Requires-Dist: globalgenie[chromadb]; extra == "vectordbs"
Requires-Dist: globalgenie[lancedb]; extra == "vectordbs"
Requires-Dist: globalgenie[qdrant]; extra == "vectordbs"
Requires-Dist: globalgenie[couchbase]; extra == "vectordbs"
Requires-Dist: globalgenie[cassandra]; extra == "vectordbs"
Requires-Dist: globalgenie[mongodb]; extra == "vectordbs"
Requires-Dist: globalgenie[singlestore]; extra == "vectordbs"
Requires-Dist: globalgenie[weaviate]; extra == "vectordbs"
Requires-Dist: globalgenie[milvusdb]; extra == "vectordbs"
Requires-Dist: globalgenie[clickhouse]; extra == "vectordbs"
Requires-Dist: globalgenie[pinecone]; extra == "vectordbs"
Requires-Dist: globalgenie[surrealdb]; extra == "vectordbs"
Provides-Extra: knowledge
Requires-Dist: globalgenie[pdf]; extra == "knowledge"
Requires-Dist: globalgenie[docx]; extra == "knowledge"
Requires-Dist: globalgenie[text]; extra == "knowledge"
Requires-Dist: globalgenie[csv]; extra == "knowledge"
Requires-Dist: globalgenie[markdown]; extra == "knowledge"
Provides-Extra: embedders
Requires-Dist: globalgenie[huggingface]; extra == "embedders"
Provides-Extra: tests
Requires-Dist: globalgenie[dev]; extra == "tests"
Requires-Dist: globalgenie[models]; extra == "tests"
Requires-Dist: globalgenie[tools]; extra == "tests"
Requires-Dist: globalgenie[storage]; extra == "tests"
Requires-Dist: globalgenie[vectordbs]; extra == "tests"
Requires-Dist: globalgenie[knowledge]; extra == "tests"
Requires-Dist: globalgenie[embedders]; extra == "tests"
Requires-Dist: globalgenie[performance]; extra == "tests"
Requires-Dist: globalgenie[readygenies]; extra == "tests"
Requires-Dist: globalgenie[agui]; extra == "tests"
Requires-Dist: twine; extra == "tests"
Requires-Dist: build; extra == "tests"
Dynamic: author
Dynamic: home-page
Dynamic: license-file
Dynamic: maintainer
Dynamic: platform
Dynamic: requires-python
